randprob/__main__.py
randprob-1.0.11.dist-info/METADATA
randprob-1.0.11.dist-info/WHEEL
randprob-1.0.11.dist-info/entry_points.txt
randprob-1.0.11.dist-info/top_level.txt
randprob-1.0.11.dist-info/RECORD
