Metadata-Version: 2.1
Name: randprob
Version: 1.0.11
Summary: Gives random problems from Division 2 in codeforces.
Home-page: https://github.com/sAksham-Ar/randprob
Author: Saksham Arya
Author-email: aryasaksham@gmail.com
License: GPLv3
Platform: UNKNOWN
Classifier: License :: OSI Approved :: GNU General Public License v3 (GPLv3)
Classifier: Programming Language :: Python :: 3
Classifier: Programming Language :: Python :: 3.8
Requires-Dist: bs4
Requires-Dist: requests
Requires-Dist: lxml
